[
  {
    "episodeId": "28038",
    "number": 1,
    "title": "How Do You Do? My Very Own Angel!",
    "streaming": "https://megaplay.buzz/stream/s-2/28038/sub"
  },
  {
    "episodeId": "28039",
    "number": 2,
    "title": "Do Your Best, Hikaru! It’s Your First Fight!",
    "streaming": "https://megaplay.buzz/stream/s-2/28039/sub"
  },
  {
    "episodeId": "28040",
    "number": 3,
    "title": "Who Are You? Misaki’s Nervous Lesson",
    "streaming": "https://megaplay.buzz/stream/s-2/28040/sub"
  },
  {
    "episodeId": "28041",
    "number": 4,
    "title": "The Day an Angel Flew Down",
    "streaming": "https://megaplay.buzz/stream/s-2/28041/sub"
  },
  {
    "episodeId": "28042",
    "number": 5,
    "title": "I Don’t Want to Lose! I’m Believing in Hikaru!",
    "streaming": "https://megaplay.buzz/stream/s-2/28042/sub"
  },
  {
    "episodeId": "28043",
    "number": 6,
    "title": "Suzuka, the Speed of Light! Hatoko’s Declaration of Rivalry!",
    "streaming": "https://megaplay.buzz/stream/s-2/28043/sub"
  },
  {
    "episodeId": "28044",
    "number": 7,
    "title": "Fight at the Edge… Misaki’s Last Chance",
    "streaming": "https://megaplay.buzz/stream/s-2/28044/sub"
  },
  {
    "episodeId": "28045",
    "number": 8,
    "title": "Misaki vs Misaki? A Dangerous Classmate",
    "streaming": "https://megaplay.buzz/stream/s-2/28045/sub"
  },
  {
    "episodeId": "28046",
    "number": 9,
    "title": "Sing, Misaki! Is the Deus an Idol?!",
    "streaming": "https://megaplay.buzz/stream/s-2/28046/sub"
  },
  {
    "episodeId": "28047",
    "number": 10,
    "title": "Mean Sisters! Hikaru, the Target",
    "streaming": "https://megaplay.buzz/stream/s-2/28047/sub"
  },
  {
    "episodeId": "28048",
    "number": 11,
    "title": "Finish It Off! Hikaru & Mao’s Important Game",
    "streaming": "https://megaplay.buzz/stream/s-2/28048/sub"
  },
  {
    "episodeId": "28049",
    "number": 12,
    "title": "Misako & Kotaro, Their Exciting Date",
    "streaming": "https://megaplay.buzz/stream/s-2/28049/sub"
  },
  {
    "episodeId": "28050",
    "number": 13,
    "title": "Pure White Blanch, Kaede’s Smile",
    "streaming": "https://megaplay.buzz/stream/s-2/28050/sub"
  },
  {
    "episodeId": "28051",
    "number": 14,
    "title": "I Won’t Give up! and an Angel Was Born",
    "streaming": "https://megaplay.buzz/stream/s-2/28051/sub"
  },
  {
    "episodeId": "28052",
    "number": 15,
    "title": "Shirahime Versus Suzuka! Secret of the Ice Machine",
    "streaming": "https://megaplay.buzz/stream/s-2/28052/sub"
  },
  {
    "episodeId": "28053",
    "number": 16,
    "title": "The Final Game! Hikaru’s Last Attack",
    "streaming": "https://megaplay.buzz/stream/s-2/28053/sub"
  },
  {
    "episodeId": "28054",
    "number": 17,
    "title": "I’ve Made My Mind up On You! the One Misaki Selected",
    "streaming": "https://megaplay.buzz/stream/s-2/28054/sub"
  },
  {
    "episodeId": "28055",
    "number": 18,
    "title": "Many Strong Opponents! the Nation Games of Everyone’s Dreams",
    "streaming": "https://megaplay.buzz/stream/s-2/28055/sub"
  },
  {
    "episodeId": "28056",
    "number": 19,
    "title": "System Down! Decisive Fight On a Ship in a Storm",
    "streaming": "https://megaplay.buzz/stream/s-2/28056/sub"
  },
  {
    "episodeId": "28057",
    "number": 20,
    "title": "Is Icchan the Enemy? the Puzzling Second Game!",
    "streaming": "https://megaplay.buzz/stream/s-2/28057/sub"
  },
  {
    "episodeId": "28058",
    "number": 21,
    "title": "Summertime at the Sea! Someone Is in Love With Someone!",
    "streaming": "https://megaplay.buzz/stream/s-2/28058/sub"
  },
  {
    "episodeId": "28059",
    "number": 22,
    "title": "Suddenly Just the Two of Us, Secret Double Dates",
    "streaming": "https://megaplay.buzz/stream/s-2/28059/sub"
  },
  {
    "episodeId": "28060",
    "number": 23,
    "title": "Break up the Magic Wall! Misaki Versus Ohjiro",
    "streaming": "https://megaplay.buzz/stream/s-2/28060/sub"
  },
  {
    "episodeId": "28061",
    "number": 24,
    "title": "Reach Misaki! This Thought Goes Over the Rainbow!",
    "streaming": "https://megaplay.buzz/stream/s-2/28061/sub"
  },
  {
    "episodeId": "28062",
    "number": 25,
    "title": "Reunion of Destiny, Angels Wet With Tears",
    "streaming": "https://megaplay.buzz/stream/s-2/28062/sub"
  },
  {
    "episodeId": "28063",
    "number": 26,
    "title": "Angel Wings! Please Guide Me & Hikaru!",
    "streaming": "https://megaplay.buzz/stream/s-2/28063/sub"
  }
]